<?xml version="1.0"?>
<SubscribedTypesCache xmlns:xsi="http://www.w3.org/2001/XMLSchema-instance" xmlns:xsd="http://www.w3.org/2001/XMLSchema">
  <Assemblies>
    <AssemblyInfo>
      <SubscribedTypes>
        <string>Composite.Plugins.Security.LoginSessionStores.WampContextBasedLoginSessionStore.WampContextBasedLoginSessionStoreRegistrator</string>
        <string>Composite.Plugins.Search.Endpoint.SearchApplicationStartup</string>
        <string>Composite.Plugins.Components.FileBasedComponentProvider.FileBasedComponentProviderRegistrator</string>
        <string>Composite.Plugins.Components.ComponentTags.TagManagerRegistrar</string>
        <string>Composite.Plugins.Components.ComponentsEndpoint.ComponentsEndpoint</string>
        <string>Composite.Plugins.Elements.ElementProviders.GeneratedDataTypesElementProvider.GeneratedDataTypesElementDynamicActionTokens</string>
        <string>Composite.Plugins.Elements.ElementProviders.PageElementProvider.PageElementDynamicActionTokens</string>
        <string>Composite.Data.ProcessControlled.ProcessControllers.GenericPublishProcessController.GenericPublishProcessDynamicActionTokens</string>
        <string>Composite.Core.WebClient.ComponentsEndpoint</string>
        <string>Composite.Core.WebClient.Services.WampRouter.WampRouterResolverRegistry</string>
        <string>Composite.C1Console.Security.Compatibility.LegacySerializedEntityTokenUpgrader</string>
        <string>Composite.C1Console.RichContent.Components.ComponentChangeNotifierRegistrator</string>
        <string>Composite.C1Console.RichContent.Components.ComponentManagerRegistrator</string>
      </SubscribedTypes>
      <AssemblyName>Composite</AssemblyName>
      <LastModified>2018-04-10T13:31:49.2544895+02:00</LastModified>
    </AssemblyInfo>
    <AssemblyInfo>
      <SubscribedTypes />
      <AssemblyName>Composite.XmlSerializers</AssemblyName>
      <LastModified>2018-04-10T13:31:49.7209693+02:00</LastModified>
    </AssemblyInfo>
    <AssemblyInfo>
      <SubscribedTypes>
        <string>Composite.Community.Blog.BlogStartupHandler</string>
      </SubscribedTypes>
      <AssemblyName>Composite.Community.Blog</AssemblyName>
      <LastModified>2018-04-10T13:33:38.1044433+02:00</LastModified>
    </AssemblyInfo>
    <AssemblyInfo>
      <SubscribedTypes>
        <string>Composite.Forms.FormBuilder.StartupHandler</string>
      </SubscribedTypes>
      <AssemblyName>Composite.Forms.FormBuilder</AssemblyName>
      <LastModified>2018-04-10T13:33:35.8533074+02:00</LastModified>
    </AssemblyInfo>
    <AssemblyInfo>
      <SubscribedTypes />
      <AssemblyName>Composite.Media.ImageCrop</AssemblyName>
      <LastModified>2018-04-10T13:33:37.7395551+02:00</LastModified>
    </AssemblyInfo>
    <AssemblyInfo>
      <SubscribedTypes />
      <AssemblyName>Composite.Tools.LinkChecker</AssemblyName>
      <LastModified>2018-04-10T13:33:41.0480941+02:00</LastModified>
    </AssemblyInfo>
    <AssemblyInfo>
      <SubscribedTypes>
        <string>Composite.Web.BundlingAndMinification.StartupHandler+StatupHandler</string>
      </SubscribedTypes>
      <AssemblyName>Composite.Web.BundlingAndMinification</AssemblyName>
      <LastModified>2018-04-10T13:33:35.2927788+02:00</LastModified>
    </AssemblyInfo>
    <AssemblyInfo>
      <SubscribedTypes>
        <string>Orckestra.Search.StartupHandler</string>
      </SubscribedTypes>
      <AssemblyName>Orckestra.Search</AssemblyName>
      <LastModified>2018-04-10T13:33:41.9935215+02:00</LastModified>
    </AssemblyInfo>
    <AssemblyInfo>
      <SubscribedTypes>
        <string>Orckestra.Search.LuceneNET.StartupHandler</string>
      </SubscribedTypes>
      <AssemblyName>Orckestra.Search.LuceneNET</AssemblyName>
      <LastModified>2018-04-10T13:33:42.0205943+02:00</LastModified>
    </AssemblyInfo>
    <AssemblyInfo>
      <SubscribedTypes />
      <AssemblyName>Orckestra.Search.WebsiteSearch</AssemblyName>
      <LastModified>2018-04-10T13:33:41.1471954+02:00</LastModified>
    </AssemblyInfo>
    <AssemblyInfo>
      <SubscribedTypes>
        <string>Orckestra.Web.Css.Less.StartupHandler+StatupHandler</string>
      </SubscribedTypes>
      <AssemblyName>Orckestra.Web.Css.Less</AssemblyName>
      <LastModified>2018-04-10T13:33:28.3231769+02:00</LastModified>
    </AssemblyInfo>
    <AssemblyInfo>
      <SubscribedTypes>
        <string>Composite.Versioning.ContentVersioning.VersioningApplicationStartupHandler</string>
      </SubscribedTypes>
      <AssemblyName>Composite.Versioning.ContentVersioning</AssemblyName>
      <LastModified>2018-04-10T17:56:06.6990358+02:00</LastModified>
    </AssemblyInfo>
  </Assemblies>
</SubscribedTypesCache>